Scraper_Ashutosh_Kumar_Singh/__init__.py
Scraper_Ashutosh_Kumar_Singh/scraper.py
Scraper_Ashutosh_kumar_Singh-1.0.3.dist-info/LICENCE
Scraper_Ashutosh_kumar_Singh-1.0.3.dist-info/METADATA
Scraper_Ashutosh_kumar_Singh-1.0.3.dist-info/WHEEL
Scraper_Ashutosh_kumar_Singh-1.0.3.dist-info/top_level.txt
Scraper_Ashutosh_kumar_Singh-1.0.3.dist-info/RECORD
